[
    {
        "id": "3278011001",
        "district_id": "327801",
        "name": "Yudanagara",
        "postal_code": ""
    },
    {
        "id": "3278011002",
        "district_id": "327801",
        "name": "Nagarawangi",
        "postal_code": ""
    },
    {
        "id": "3278011003",
        "district_id": "327801",
        "name": "Cilembang",
        "postal_code": ""
    },
    {
        "id": "3278011004",
        "district_id": "327801",
        "name": "Argasari",
        "postal_code": ""
    },
    {
        "id": "3278011005",
        "district_id": "327801",
        "name": "Tugujaya",
        "postal_code": ""
    },
    {
        "id": "3278011006",
        "district_id": "327801",
        "name": "Tuguraja",
        "postal_code": ""
    }
]