[
    {
        "id": "1272021001",
        "district_id": "127202",
        "name": "Dwikora",
        "postal_code": ""
    },
    {
        "id": "1272021002",
        "district_id": "127202",
        "name": "Proklamasi",
        "postal_code": ""
    },
    {
        "id": "1272021003",
        "district_id": "127202",
        "name": "Bantan",
        "postal_code": ""
    },
    {
        "id": "1272021004",
        "district_id": "127202",
        "name": "Timbang Galung",
        "postal_code": ""
    },
    {
        "id": "1272021005",
        "district_id": "127202",
        "name": "Simarito",
        "postal_code": ""
    },
    {
        "id": "1272021006",
        "district_id": "127202",
        "name": "Sipinggolpinggol (Sipinggol Pinggol)",
        "postal_code": ""
    },
    {
        "id": "1272021007",
        "district_id": "127202",
        "name": "Banjar",
        "postal_code": ""
    },
    {
        "id": "1272021008",
        "district_id": "127202",
        "name": "Teladan",
        "postal_code": ""
    }
]