[
    {
        "id": "3273101001",
        "district_id": "327310",
        "name": "Karasak",
        "postal_code": ""
    },
    {
        "id": "3273101002",
        "district_id": "327310",
        "name": "Nyengseret",
        "postal_code": ""
    },
    {
        "id": "3273101003",
        "district_id": "327310",
        "name": "Karanganyar",
        "postal_code": ""
    },
    {
        "id": "3273101004",
        "district_id": "327310",
        "name": "Panjunan",
        "postal_code": ""
    },
    {
        "id": "3273101005",
        "district_id": "327310",
        "name": "Cibadak",
        "postal_code": ""
    },
    {
        "id": "3273101006",
        "district_id": "327310",
        "name": "Pelindung Hewan",
        "postal_code": ""
    }
]