[
    {
        "id": "9601502001",
        "district_id": "960150",
        "name": "Tarsa",
        "postal_code": null
    },
    {
        "id": "9601502002",
        "district_id": "960150",
        "name": "Klamne",
        "postal_code": null
    },
    {
        "id": "9601502003",
        "district_id": "960150",
        "name": "Wisbiak",
        "postal_code": null
    },
    {
        "id": "9601502004",
        "district_id": "960150",
        "name": "Klafyo",
        "postal_code": null
    },
    {
        "id": "9601502005",
        "district_id": "960150",
        "name": "Mlasiwor",
        "postal_code": null
    },
    {
        "id": "9601502006",
        "district_id": "960150",
        "name": "Klafelem",
        "postal_code": null
    },
    {
        "id": "9601502007",
        "district_id": "960150",
        "name": "Klaflum",
        "postal_code": null
    },
    {
        "id": "9601502008",
        "district_id": "960150",
        "name": "Klarin",
        "postal_code": null
    },
    {
        "id": "9601502009",
        "district_id": "960150",
        "name": "Mlaron",
        "postal_code": null
    }
]