[
    {
        "id": "3324132001",
        "district_id": "332413",
        "name": "Pandes",
        "postal_code": ""
    },
    {
        "id": "3324132002",
        "district_id": "332413",
        "name": "Podosari",
        "postal_code": ""
    },
    {
        "id": "3324132003",
        "district_id": "332413",
        "name": "Botomulyo",
        "postal_code": ""
    },
    {
        "id": "3324132004",
        "district_id": "332413",
        "name": "Cepiring",
        "postal_code": ""
    },
    {
        "id": "3324132005",
        "district_id": "332413",
        "name": "Damarsari",
        "postal_code": ""
    },
    {
        "id": "3324132006",
        "district_id": "332413",
        "name": "Karangayu",
        "postal_code": ""
    },
    {
        "id": "3324132007",
        "district_id": "332413",
        "name": "Karangsuno",
        "postal_code": ""
    },
    {
        "id": "3324132008",
        "district_id": "332413",
        "name": "Gondang",
        "postal_code": ""
    },
    {
        "id": "3324132009",
        "district_id": "332413",
        "name": "Sidomulyo",
        "postal_code": ""
    },
    {
        "id": "3324132010",
        "district_id": "332413",
        "name": "Juwiring",
        "postal_code": ""
    },
    {
        "id": "3324132011",
        "district_id": "332413",
        "name": "Kaliayu",
        "postal_code": ""
    },
    {
        "id": "3324132012",
        "district_id": "332413",
        "name": "Kalirandugede (Kalirandu Gede)",
        "postal_code": ""
    },
    {
        "id": "3324132013",
        "district_id": "332413",
        "name": "Korowelangkulon (Korowelang Kulon)",
        "postal_code": ""
    },
    {
        "id": "3324132014",
        "district_id": "332413",
        "name": "Korowelanganyar (Korowelang Anyar)",
        "postal_code": ""
    },
    {
        "id": "3324132015",
        "district_id": "332413",
        "name": "Margorejo",
        "postal_code": ""
    }
]