[
    {
        "id": "3513232001",
        "district_id": "351323",
        "name": "Sumberrejo (Sumberejo)",
        "postal_code": ""
    },
    {
        "id": "3513232002",
        "district_id": "351323",
        "name": "Sumendi",
        "postal_code": ""
    },
    {
        "id": "3513232003",
        "district_id": "351323",
        "name": "Bayeman",
        "postal_code": ""
    },
    {
        "id": "3513232004",
        "district_id": "351323",
        "name": "Dungun",
        "postal_code": ""
    },
    {
        "id": "3513232005",
        "district_id": "351323",
        "name": "Curahdringu (Curah Dringu)",
        "postal_code": ""
    },
    {
        "id": "3513232006",
        "district_id": "351323",
        "name": "Wringinanom",
        "postal_code": ""
    },
    {
        "id": "3513232007",
        "district_id": "351323",
        "name": "Sumberkramat",
        "postal_code": ""
    },
    {
        "id": "3513232008",
        "district_id": "351323",
        "name": "Tongaswetan (Tongas Wetan)",
        "postal_code": ""
    },
    {
        "id": "3513232009",
        "district_id": "351323",
        "name": "Pamatan",
        "postal_code": ""
    },
    {
        "id": "3513232010",
        "district_id": "351323",
        "name": "Klampok",
        "postal_code": ""
    },
    {
        "id": "3513232011",
        "district_id": "351323",
        "name": "Tongaskulon (Tongas Kulon)",
        "postal_code": ""
    },
    {
        "id": "3513232012",
        "district_id": "351323",
        "name": "Curahtulis (Curah Tulis)",
        "postal_code": ""
    },
    {
        "id": "3513232013",
        "district_id": "351323",
        "name": "Tambakrejo",
        "postal_code": ""
    },
    {
        "id": "3513232014",
        "district_id": "351323",
        "name": "Tanjungrejo",
        "postal_code": ""
    }
]